span_converter/__init__.py
span_converter/span_converter.py
span_converter-0.1.0.dist-info/METADATA
span_converter-0.1.0.dist-info/WHEEL
span_converter-0.1.0.dist-info/top_level.txt
span_converter-0.1.0.dist-info/RECORD
